[
    {
      "name": "customer_key",
      "mode": "REQUIRED",
      "type": "INTEGER",
      "description": null,
      "fields": []
    },
    {
      "name": "customer_id",
      "mode": "NULLABLE",
      "type": "INTEGER",
      "description": null,
      "fields": []
    },
    {
      "name": "customer_name",
      "mode": "REQUIRED",
      "type": "STRING",
      "description": null,
      "fields": []
    },
    {
      "name": "email",
      "mode": "NULLABLE",
      "type": "STRING",
      "description": null,
      "fields": []
    },
    {
      "name": "phone",
      "mode": "NULLABLE",
      "type": "STRING",
      "description": null,
      "fields": []
    },
    {
      "name": "address_id",
      "mode": "NULLABLE",
      "type": "INTEGER",
      "description": null,
      "fields": []
    },
    {
      "name": "address_street",
      "mode": "NULLABLE",
      "type": "STRING",
      "description": null,
      "fields": []
    },
    {
      "name": "address_zipcode",
      "mode": "NULLABLE",
      "type": "STRING",
      "description": null,
      "fields": []
    },
    {
      "name": "city_id",
      "mode": "NULLABLE",
      "type": "INTEGER",
      "description": null,
      "fields": []
    },
    {
      "name": "city_name",
      "mode": "NULLABLE",
      "type": "STRING",
      "description": null,
      "fields": []
    },
    {
      "name": "state_id",
      "mode": "NULLABLE",
      "type": "INTEGER",
      "description": null,
      "fields": []
    },
    {
      "name": "state_name",
      "mode": "NULLABLE",
      "type": "STRING",
      "description": null,
      "fields": []
    },
    {
      "name": "country_id",
      "mode": "NULLABLE",
      "type": "INTEGER",
      "description": null,
      "fields": []
    },
    {
      "name": "country_name",
      "mode": "NULLABLE",
      "type": "STRING",
      "description": null,
      "fields": []
    },
    {
      "name": "created_at",
      "mode": "NULLABLE",
      "type": "TIMESTAMP",
      "description": null,
      "fields": []
    },
    {
      "name": "modified_by",
      "mode": "NULLABLE",
      "type": "STRING",
      "description": null,
      "fields": []
    },
    {
      "name": "modified_at",
      "mode": "NULLABLE",
      "type": "TIMESTAMP",
      "description": null,
      "fields": []
    }
  ]